mouselocker/MainWindow.py
mouselocker/__init__.py
mouselocker/app.py
mouselocker/linux.py
mouselocker/images/1.ico
mouselocker/images/2.ico
mouselocker/images/3.ico
mouselocker-0.2.2.data/scripts/mouselocker
mouselocker-0.2.2.dist-info/LICENSE
mouselocker-0.2.2.dist-info/METADATA
mouselocker-0.2.2.dist-info/WHEEL
mouselocker-0.2.2.dist-info/top_level.txt
mouselocker-0.2.2.dist-info/RECORD
