Metadata-Version: 2.1
Name: mouselocker
Version: 0.2.2
Summary: Mouse Locker Program
Home-page: https://github.com/vistoyn/mouselocker2
Author: Ildar Bikmamatov
Author-email: vistoyn@gmail.com
License: GNU General Public License v3
Platform: UNKNOWN
Classifier: Development Status :: 3 - Alpha
Classifier: Environment :: X11 Applications
Classifier: License :: OSI Approved :: GNU General Public License v3 or later (GPLv3+)
Classifier: Operating System :: POSIX :: Linux
Classifier: Programming Language :: Python
Classifier: Programming Language :: Python :: 3
Classifier: Topic :: Utilities
Requires-Dist: PyQt5
Requires-Dist: python-xlib
